swiftshadow/__init__.py
swiftshadow/cache.py
swiftshadow/classes.py
swiftshadow/exceptions.py
swiftshadow/helpers.py
swiftshadow/models.py
swiftshadow/providers.py
swiftshadow/types.py
swiftshadow/utils.py
swiftshadow/validator.py
swiftshadow-2.4.0.dist-info/METADATA
swiftshadow-2.4.0.dist-info/WHEEL
swiftshadow-2.4.0.dist-info/entry_points.txt
swiftshadow-2.4.0.dist-info/licenses/LICENSE
swiftshadow-2.4.0.dist-info/RECORD
