Metadata-Version: 2.4
Name: swiftshadow
Version: 2.4.0
Summary: Free IP Proxy rotator for python
Author-email: sachin-sankar <mail.sachinsankar@gmail.com>
License-File: LICENSE
Requires-Python: >=3.10
Requires-Dist: aiofiles>=24.1.0
Requires-Dist: aiohttp>=3.11.11
Requires-Dist: appdirs>=1.4.4
Requires-Dist: lxml>=6.0.0
Requires-Dist: requests>=2.32.3
